stcorr/__init__.py
stcorr/example.py
stcorr/stc.py
stcorr-0.0.0.dist-info/METADATA
stcorr-0.0.0.dist-info/RECORD
stcorr-0.0.0.dist-info/WHEEL
stcorr-0.0.0.dist-info/top_level.txt
