Metadata-Version: 2.1
Name: stcorr
Version: 0.0.0
Summary: Spatial and Temporal Correlation Analysis
Home-page: https://github.com/xuefeicao/stc
Author: Jun Ke, Xuefei Cao, Xi Luo
License: UNKNOWN
Platform: UNKNOWN
Requires-Dist: numpy (>=1.11.1)
Requires-Dist: scipy (>=0.19.0)
